turtletree/__init__.py
turtletree/meta_singleton.py
turtletree/stdRV.py
turtletree/subprocess.py
turtletree/array/__init__.py
turtletree/array/array_dict_data.py
turtletree/array/array_to_image.py
turtletree/array/axis_rotation.py
turtletree/array/labeledTensor.py
turtletree/array/text_matrix_expression.py
turtletree/database/__init__.py
turtletree/database/db.py
turtletree/database/item.py
turtletree/database/table.py
turtletree-0.1.0.dist-info/LICENSE.txt
turtletree-0.1.0.dist-info/METADATA
turtletree-0.1.0.dist-info/WHEEL
turtletree-0.1.0.dist-info/top_level.txt
turtletree-0.1.0.dist-info/RECORD
