Metadata-Version: 2.1
Name: turtletree
Version: 0.1.0
Summary: Data transform library written by Jaehak Lee
Home-page: https://github.com/jaehakl/turtletree
Author: Jaehak Lee
Author-email: leejaehak87@gmail.com
Keywords: data,database,array,matrix
Classifier: Operating System :: OS Independent
Classifier: Programming Language :: Python :: 3 :: Only
Classifier: License :: OSI Approved :: Apache Software License
Requires-Python: >=3.6
License-File: LICENSE.txt
Requires-Dist: numpy
Requires-Dist: pandas
Requires-Dist: matplotlib
